confluent_kafka-stubs/__init__.pyi
confluent_kafka-stubs/_config.pyi
confluent_kafka-stubs/cimpl.pyi
confluent_kafka-stubs/deserializing_consumer.pyi
confluent_kafka-stubs/error.pyi
confluent_kafka-stubs/py.typed
confluent_kafka-stubs/serializing_producer.pyi
confluent_kafka-stubs/_model/__init__.pyi
confluent_kafka-stubs/admin/__init__.pyi
confluent_kafka-stubs/admin/_acl.pyi
confluent_kafka-stubs/admin/_cluster.pyi
confluent_kafka-stubs/admin/_config.pyi
confluent_kafka-stubs/admin/_group.pyi
confluent_kafka-stubs/admin/_listoffsets.pyi
confluent_kafka-stubs/admin/_metadata.pyi
confluent_kafka-stubs/admin/_records.pyi
confluent_kafka-stubs/admin/_resource.pyi
confluent_kafka-stubs/admin/_scram.pyi
confluent_kafka-stubs/admin/_topic.pyi
confluent_kafka-stubs/avro/__init__.pyi
confluent_kafka-stubs/avro/cached_schema_registry_client.pyi
confluent_kafka-stubs/avro/error.pyi
confluent_kafka-stubs/avro/load.pyi
confluent_kafka-stubs/avro/serializer/__init__.pyi
confluent_kafka-stubs/avro/serializer/message_serializer.pyi
confluent_kafka-stubs/schema_registry/__init__.pyi
confluent_kafka-stubs/schema_registry/error.pyi
confluent_kafka-stubs/schema_registry/schema_registry_client.pyi
confluent_kafka-stubs/serialization/__init__.pyi
kafka_stubs-2.10.0.1.dist-info/licenses/LICENSE
kafka_stubs-2.10.0.1.dist-info/METADATA
kafka_stubs-2.10.0.1.dist-info/WHEEL
kafka_stubs-2.10.0.1.dist-info/top_level.txt
kafka_stubs-2.10.0.1.dist-info/RECORD
